gheymat/__init__.py
gheymat/crypto.py
gheymat/currency.py
gheymat/exchange.py
gheymat/metal.py
gheymat-0.3.8.dist-info/licenses/LICENSE
gheymat-0.3.8.dist-info/METADATA
gheymat-0.3.8.dist-info/WHEEL
gheymat-0.3.8.dist-info/top_level.txt
gheymat-0.3.8.dist-info/RECORD
