Metadata-Version: 2.4
Name: gheymat
Version: 0.3.8
Summary: کتابخانه‌ای برای دریافت قیمت ارزها و طلا و...
Author-email: Ali Heydari <imrrobat@gmail.com>
License: MIT
Project-URL: Homepage, https://github.com/imrrobat/gheymat
Requires-Python: >=3.7
License-File: LICENSE
Requires-Dist: requests
Requires-Dist: beautifulsoup4
Dynamic: license-file
